pyredblack/__init__.py
pyredblack/redblack.so
pyredblack/tests/__init__.py
pyredblack/tests/testdict.py
pyredblack/tests/testset.py
pyredblack-0.1.1.dist-info/DESCRIPTION.rst
pyredblack-0.1.1.dist-info/METADATA
pyredblack-0.1.1.dist-info/metadata.json
pyredblack-0.1.1.dist-info/RECORD
pyredblack-0.1.1.dist-info/top_level.txt
pyredblack-0.1.1.dist-info/WHEEL
