Metadata-Version: 1.1
Name: pyredblack
Version: 0.1.1
Summary: Red/black trees in C++ for Python
Home-page: https://github.com/wroberts/pyredblack
Author: Will Roberts
Author-email: wildwilhelm@gmail.com
License: MIT
Keywords: data structure algorithm
Platform: UNKNOWN
Classifier: Development Status :: 3 - Alpha
Classifier: Intended Audience :: Developers
Classifier: Topic :: Software Development :: Build Tools
Classifier: License :: OSI Approved :: MIT License
Classifier: Programming Language :: Python :: 2
Classifier: Programming Language :: Python :: 2.7
Classifier: Programming Language :: Python :: 3
Classifier: Programming Language :: Python :: 3.2
Classifier: Programming Language :: Python :: 3.3
Classifier: Programming Language :: Python :: 3.4
